tghtml/__init__.py
tghtml/core.py
tghtml-1.2.1.dist-info/LICENSE
tghtml-1.2.1.dist-info/METADATA
tghtml-1.2.1.dist-info/WHEEL
tghtml-1.2.1.dist-info/RECORD
